{"id":62318752,"login":"hungnv-wk","contributions":{"total":1,"by_kind":{"commit":0,"issue":1,"pull_request":0}},"repositories":["openwallet-foundation-labs/identity-credential"],"years":[2022],"first_contribution":{"kind":"issue","owner":"openwallet-foundation-labs","repository":"identity-credential","sha":null,"number":180,"title":"java.lang.IllegalArgumentException: Navigation action/destination com.android.mdl.appreader:id/action_Transfer_to_RequestOptions cannot be found from the current destination Destination(com.android.mdl.appreader:id/RequestOptions)","ts":1672041314}}